openkosmos_core/__init__.py
openkosmos_core/arguments.py
openkosmos_core/auth.py
openkosmos_core/common/__init__.py
openkosmos_core/common/model.py
openkosmos_core/config.py
openkosmos_core/exception.py
openkosmos_core/executor.py
openkosmos_core/html_extractor.py
openkosmos_core/py.typed
openkosmos_core/setting.py
openkosmos_core/templatex.py
openkosmos_core-0.1.4.dist-info/WHEEL
openkosmos_core-0.1.4.dist-info/METADATA
openkosmos_core-0.1.4.dist-info/RECORD
