Metadata-Version: 2.3
Name: openkosmos-core
Version: 0.1.4
Summary: openkosmos-core
Author: wangtao
Author-email: wangtao <wangtao@openkosmos.com>
Requires-Dist: cryptography>=45.0.7
Requires-Dist: parsel>=1.10.0
Requires-Dist: pydantic>=2.12.5
Requires-Dist: pyjwt>=2.10.1
Requires-Dist: pyyaml>=6.0.3
Requires-Dist: tqdm>=4.67.1
Requires-Python: ==3.12.*
